ayenaspring/__init__.py
ayenaspring/_openai_scripts.py
ayenaspring/api_requestor.py
ayenaspring/cli.py
ayenaspring/embeddings_utils.py
ayenaspring/error.py
ayenaspring/object_classes.py
ayenaspring/openai_object.py
ayenaspring/openai_response.py
ayenaspring/upload_progress.py
ayenaspring/util.py
ayenaspring/validators.py
ayenaspring/version.py
ayenaspring/wandb_logger.py
ayenaspring/api_resources/__init__.py
ayenaspring/api_resources/audio.py
ayenaspring/api_resources/chat_completion.py
ayenaspring/api_resources/completion.py
ayenaspring/api_resources/customer.py
ayenaspring/api_resources/deployment.py
ayenaspring/api_resources/edit.py
ayenaspring/api_resources/embedding.py
ayenaspring/api_resources/engine.py
ayenaspring/api_resources/error_object.py
ayenaspring/api_resources/file.py
ayenaspring/api_resources/fine_tune.py
ayenaspring/api_resources/fine_tuning.py
ayenaspring/api_resources/image.py
ayenaspring/api_resources/model.py
ayenaspring/api_resources/moderation.py
ayenaspring/api_resources/abstract/__init__.py
ayenaspring/api_resources/abstract/api_resource.py
ayenaspring/api_resources/abstract/createable_api_resource.py
ayenaspring/api_resources/abstract/deletable_api_resource.py
ayenaspring/api_resources/abstract/engine_api_resource.py
ayenaspring/api_resources/abstract/listable_api_resource.py
ayenaspring/api_resources/abstract/nested_resource_class_methods.py
ayenaspring/api_resources/abstract/paginatable_api_resource.py
ayenaspring/api_resources/abstract/updateable_api_resource.py
ayenaspring/api_resources/experimental/__init__.py
ayenaspring/api_resources/experimental/completion_config.py
ayenaspring/datalib/__init__.py
ayenaspring/datalib/common.py
ayenaspring/datalib/numpy_helper.py
ayenaspring/datalib/pandas_helper.py
ayenaspring/tests/__init__.py
ayenaspring/tests/test_api_requestor.py
ayenaspring/tests/test_endpoints.py
ayenaspring/tests/test_exceptions.py
ayenaspring/tests/test_file_cli.py
ayenaspring/tests/test_long_examples_validator.py
ayenaspring-1.0.0.dist-info/METADATA
ayenaspring-1.0.0.dist-info/WHEEL
ayenaspring-1.0.0.dist-info/top_level.txt
ayenaspring-1.0.0.dist-info/RECORD
