Metadata-Version: 2.1
Name: ayenaspring
Version: 1.0.0
Summary: run_package
Home-page: https://github.com/openai/openai-python
Author: liangliang137
Author-email: 1102071917@qq.com
License: UNKNOWN
Platform: UNKNOWN
Requires-Python: >=3.7
Requires-Dist: requests
Requires-Dist: aiohttp
Requires-Dist: typing-extensions
Requires-Dist: tqdm
Requires-Dist: urllib3 (==1.26.15)
